agriculture_data_analytics/__init__.py
agriculture_data_analytics/cso_ie.py
agriculture_data_analytics/dataframe_labels.py
agriculture_data_analytics/project_manager.py
agriculture_data_analytics/sentiment_analysis.py
agriculture_data_analytics-0.0.1.dist-info/METADATA
agriculture_data_analytics-0.0.1.dist-info/WHEEL
agriculture_data_analytics-0.0.1.dist-info/license
agriculture_data_analytics-0.0.1.dist-info/top_level.txt
agriculture_data_analytics-0.0.1.dist-info/RECORD
