Metadata-Version: 2.1
Name: agriculture-data-analytics
Version: 0.0.1
Summary: Data analytic functions for the project.
Home-page: https://github.com/markcrowe-com/data-analytics-project-template/
Author: Mark Crowe
Author-email: YOUR_EMAIL@users.noreply.github.com
License: UNKNOWN
Project-URL: Bug Tracker, https://github.com/markcrowe-com/data-analytics-project-template/issues
Platform: UNKNOWN
Classifier: Programming Language :: Python :: 3
Classifier: Operating System :: OS Independent
Requires-Python: >=3.6
License-File: license
